dps/__init__.py
dps/utils.py
dps/pxfusion/__init__.py
dps/pxfusion/client.py
dps/pxfusion/transactions.py
dps/pxpost/__init__.py
dps/pxpost/client.py
dps/pxpost/transactions.py
dps/transactions/__init__.py
dps/transactions/base.py
dps/transactions/constants.py
dps/transactions/decorators.py
dps/transactions/fields.py
dps/vendors/__init__.py
dps/vendors/inflection.py
dps/vendors/suds_requests.py
dps/vendors/xmltodict.py
dps_pxpy-0.2.1.dist-info/DESCRIPTION.rst
dps_pxpy-0.2.1.dist-info/METADATA
dps_pxpy-0.2.1.dist-info/pydist.json
dps_pxpy-0.2.1.dist-info/RECORD
dps_pxpy-0.2.1.dist-info/top_level.txt
dps_pxpy-0.2.1.dist-info/WHEEL
tests/__init__.py
tests/test_pxfusion.py
tests/test_pxpost.py
tests/test_transactions.py
tests/test_utils.py
