Metadata-Version: 2.0
Name: dps-pxpy
Version: 0.2.1
Summary: Python low-level client for DPS Payment Express PxPost and PxFusion API's
Home-page: https://github.com/OohlaLabs/dps-pxpy/
Author: Thierry Jossermoz
Author-email: thierry.jossermoz@oohlalabs.com
License: MIT
Platform: UNKNOWN
Classifier: License :: OSI Approved :: MIT License
Classifier: Development Status :: 5 - Production/Stable
Classifier: Environment :: Web Environment
Classifier: Intended Audience :: Developers
Classifier: Operating System :: OS Independent
Classifier: Programming Language :: Python
Classifier: Programming Language :: Python :: 2.7
Classifier: Programming Language :: Python :: 3.3
Classifier: Programming Language :: Python :: 3.4
Classifier: Topic :: Software Development :: Libraries :: Python Modules
Requires-Dist: requests (>=2.2.0)
Requires-Dist: suds-jurko (>=0.5)
Requires-Dist: six (>=1.5)
